evodcinv/VERSION
evodcinv/__about__.py
evodcinv/__init__.py
evodcinv/_common.py
evodcinv/_curve.py
evodcinv/_helpers.py
evodcinv/_layer.py
evodcinv/_model.py
evodcinv/_progress.py
evodcinv/_result.py
evodcinv/_io/__init__.py
evodcinv/_io/_helpers.py
evodcinv/_io/h5/__init__.py
evodcinv/_io/h5/_h5.py
evodcinv/_io/json/__init__.py
evodcinv/_io/json/_json.py
evodcinv/factory/__init__.py
evodcinv/factory/_extra_terms.py
evodcinv-2.2.2.dist-info/LICENSE
evodcinv-2.2.2.dist-info/METADATA
evodcinv-2.2.2.dist-info/WHEEL
evodcinv-2.2.2.dist-info/top_level.txt
evodcinv-2.2.2.dist-info/RECORD
