Metadata-Version: 2.1
Name: evodcinv
Version: 2.2.2
Summary: Inversion of dispersion curves using Evolutionary Algorithms
Home-page: https://github.com/keurfonluu/evodcinv
Author: Keurfon Luu
License: BSD 3-Clause License
Project-URL: Code, https://github.com/keurfonluu/evodcinv
Project-URL: Issues, https://github.com/keurfonluu/evodcinv/issues
Platform: any
Classifier: License :: OSI Approved :: BSD License
Classifier: Operating System :: OS Independent
Classifier: Development Status :: 5 - Production/Stable
Classifier: Intended Audience :: Science/Research
Classifier: Topic :: Scientific/Engineering
Classifier: Topic :: Scientific/Engineering :: Physics
Classifier: Programming Language :: Python :: 3.7
Classifier: Programming Language :: Python :: 3.8
Classifier: Programming Language :: Python :: 3.9
Classifier: Programming Language :: Python :: 3.10
Classifier: Programming Language :: Python :: 3.11
Requires-Python: >=3.7
License-File: LICENSE
Requires-Dist: importlib-metadata
Requires-Dist: numpy
Requires-Dist: matplotlib
Requires-Dist: joblib
Requires-Dist: h5py
Requires-Dist: progress
Requires-Dist: disba >=0.6.1
Requires-Dist: stochopy >=2.3.0
